[{"作者":"hrylin","文章id":43223863,"文章標題":"花蓮三日遊行程安排。一起走訪美麗的後山","貼文時間":"2016-01-10T15:30:56.000Z","連結":"http:\/\/hrylin.pixnet.net\/blog\/post\/43223863"},{"作者":"hrylin","文章id":43244725,"文章標題":"花蓮鳳林特色民宿雪雲城堡、何留民宿、麥區火柴盒民宿。付出心思打造出夢想旅遊天地","貼文時間":"2016-01-04T19:49:00.000Z","連結":"http:\/\/hrylin.pixnet.net\/blog\/post\/43244725"},{"作者":"QQrice0416","文章id":43299415,"文章標題":" 巴拉告捕魚體驗&濕地導覽~『馬太鞍濕地生態園區』(花蓮光復2015-08)","貼文時間":"2016-01-15T13:01:18.000Z","連結":"http:\/\/qqrice0416.pixnet.net\/blog\/post\/43299415"},{"作者":"QQrice0416","文章id":43253755,"文章標題":" 在七星海畔來杯羊奶咖啡~『原野牧場』(花蓮新城2015-08)","貼文時間":"2016-01-03T20:18:20.000Z","連結":"http:\/\/qqrice0416.pixnet.net\/blog\/post\/43253755"},{"作者":"rita11836","文章id":43284043,"文章標題":"《住宿》花蓮市Realive B&B (志耕農Realive. 背包客)，房間充滿溫馨鄉村風的環境，每人平均不到千元的平價住宿！(含免費早餐)","貼文時間":"2016-01-12T21:30:00.000Z","連結":"http:\/\/rita11836.pixnet.net\/blog\/post\/43284043"},{"作者":"tinie0810","文章id":348462224,"文章標題":"2014花東花海季。大農大富平地森林~七彩圖騰+金黃花田璀璨齊放","貼文時間":"2014-01-26T17:50:13.000Z","連結":"http:\/\/tinie0810.pixnet.net\/blog\/post\/348462224"},{"作者":"wu840531wu890515","文章id":443259785,"文章標題":"【台東三日遊】抓住暑假的尾巴追著颱風跑(加碼衝到花蓮赤柯山賞金針花海)","貼文時間":"2016-01-28T12:41:17.000Z","連結":"http:\/\/wu840531wu890515.pixnet.net\/blog\/post\/443259785"},{"作者":"paulyearkimo","文章id":442181987,"文章標題":"花蓮光復美食 大陸餃子館 水餃\/蔥油餅在地傳統北方麵點","貼文時間":"2016-01-11T22:08:00.000Z","連結":"http:\/\/www.paulyear.com\/blog\/post\/442181987-%e8%8a%b1%e8%93%ae%e5%85%89%e5%be%a9%e7%be%8e%e9%a3%9f-%e5%a4%a7%e9%99%b8%e9%a4%83%e5%ad%90%e9%a4%a8-%e6%b0%b4%e9%a4%83-%e8%94%a5%e6%b2%b9%e9%a4%85%ef%bd%9e%e5%9c%a8%e5%9c%b0"}]