[{"作者":"pure816","文章id":43196236,"文章標題":"[新竹] 鮮滋味 烤菜盒＆蛋餅專賣店 再訪變好吃了　（2\/6前有特惠）","貼文時間":"2016-01-31T19:29:18.000Z","連結":"http:\/\/pure816.pixnet.net\/blog\/post\/43196236"},{"作者":"pure816","文章id":43347697,"文章標題":"[新竹] 芙洛麗烘焙坊 關新路二店不止有麵包、甜點、飲品，還有舒適用餐環境及兒童遊戲區","貼文時間":"2016-01-29T10:51:53.000Z","連結":"http:\/\/pure816.pixnet.net\/blog\/post\/43347697"},{"作者":"pure816","文章id":43344043,"文章標題":"[新竹巨城旁] 吳媽小火鍋 不吃紅蟳、大蝦鍋，來吃大中卷海鮮鍋","貼文時間":"2016-01-26T20:27:27.000Z","連結":"http:\/\/pure816.pixnet.net\/blog\/post\/43344043"},{"作者":"pure816","文章id":43340818,"文章標題":"[新竹] 食巢 無國界料理（北方泰食館 二店）","貼文時間":"2016-01-25T22:21:38.000Z","連結":"http:\/\/pure816.pixnet.net\/blog\/post\/43340818"},{"作者":"pure816","文章id":43331566,"文章標題":"[新竹] 臻靚風尚鍋 有霜淇淋，主配料好豐盛，主食可選烏龍麵的小火鍋","貼文時間":"2016-01-22T20:57:27.000Z","連結":"http:\/\/pure816.pixnet.net\/blog\/post\/43331566"},{"作者":"pure816","文章id":43324138,"文章標題":"[新竹] 8NaNa八樂那咖啡複合店 鄉民9折","貼文時間":"2016-01-20T22:01:26.000Z","連結":"http:\/\/pure816.pixnet.net\/blog\/post\/43324138"},{"作者":"pure816","文章id":43305952,"文章標題":"[新竹] PATiO 帕堤歐 咖啡 蛋糕烘焙（原多那之） 1\/16 咖啡買1送1","貼文時間":"2016-01-15T21:36:17.000Z","連結":"http:\/\/pure816.pixnet.net\/blog\/post\/43305952"},{"作者":"pure816","文章id":43291543,"文章標題":"[新竹] 原味燉品屋(建中店) 有宵夜場","貼文時間":"2016-01-13T18:28:07.000Z","連結":"http:\/\/pure816.pixnet.net\/blog\/post\/43291543"},{"作者":"pure816","文章id":43275835,"文章標題":"[新竹] 早安！美芝城 (東南店) 推滿滿蔬菜","貼文時間":"2016-01-11T23:05:30.000Z","連結":"http:\/\/pure816.pixnet.net\/blog\/post\/43275835"},{"作者":"pure816","文章id":38128143,"文章標題":"[新竹清夜] 香香活力早餐 推蔬果三明治","貼文時間":"2016-01-05T21:22:50.000Z","連結":"http:\/\/pure816.pixnet.net\/blog\/post\/38128143"},{"作者":"pure816","文章id":43260577,"文章標題":"[新竹] 新竹牧場 賣麵包、滷味、涼麵、......，好像不賣鮮奶","貼文時間":"2016-01-04T21:58:33.000Z","連結":"http:\/\/pure816.pixnet.net\/blog\/post\/43260577"},{"作者":"saliha","文章id":443746589,"文章標題":"*新竹寶山鄉餐廳推薦*六星集風味餐廳(用餐篇)~美味創意料理，住宿有送早晚餐喔","貼文時間":"2016-01-04T14:42:00.000Z","連結":"http:\/\/saliha.pixnet.net\/blog\/post\/443746589"},{"作者":"sophiadayy","文章id":5563847,"文章標題":"『新竹食記』凸鼻子現烘咖啡。打造一杯專屬於自己的精品咖啡","貼文時間":"2016-01-20T22:10:00.000Z","連結":"http:\/\/sophiadayy.pixnet.net\/blog\/post\/5563847"},{"作者":"thudadai","文章id":62523215,"文章標題":"[聚餐食記] 新竹－龍鳳食堂","貼文時間":"2016-01-24T21:21:34.000Z","連結":"http:\/\/thudadai.pixnet.net\/blog\/post\/62523215"},{"作者":"TimmyVong","文章id":442865111,"文章標題":"竹北美食|大滿足食堂-平價厚切日式咖哩豬排及很多肉肉丼飯份量讓人滿足．日式拉麵(豚骨\/味噌\/醬油)．烤雞串．南瓜可樂餅(百花窯旁\/無低消\/無服務費\/邀約)--踢小米食記","貼文時間":"2016-01-29T07:09:26.000Z","連結":"http:\/\/timmyvong.pixnet.net\/blog\/post\/442865111"},{"作者":"TimmyVong","文章id":443355218,"文章標題":"新竹美食|嘉義老牌石頭火鍋(新竹站前店)-肉香清甜湯頭平價又好吃(餐廳推薦\/小火鍋\/白飯\/冰淇淋免費供應\/無服務費)--踢小米食記","貼文時間":"2016-01-28T10:29:38.000Z","連結":"http:\/\/timmyvong.pixnet.net\/blog\/post\/443355218"},{"作者":"TimmyVong","文章id":443076536,"文章標題":"新竹宅配美食|愛泡菜-來自日職料理師父專業現切手工醃製水果泡菜．天然食材無味精健康又養生．韓式．黃金泡菜．柴魚蒜頭．柚子蘿蔔．紅酒紫蘇梅牛蒡．白玉蘿蔔--踢小米食記","貼文時間":"2016-01-26T15:38:17.000Z","連結":"http:\/\/timmyvong.pixnet.net\/blog\/post\/443076536"},{"作者":"uioiu","文章id":31328547,"文章標題":"【新竹。大遠百附近】飛翔的魚美式餐廳 早午餐\/鐵鍋焗飯\/親子餐 好選擇","貼文時間":"2016-01-30T00:46:24.000Z","連結":"http:\/\/uioiu.pixnet.net\/blog\/post\/31328547"},{"作者":"uioiu","文章id":30525433,"文章標題":"【新竹。竹北】在地美食，用炭火陶鍋的ㄚ祥薑母鴨\/阿祥薑母鴨\/羊肉爐\/養生雞-冬令進補正著時！","貼文時間":"2016-01-20T19:41:01.000Z","連結":"http:\/\/uioiu.pixnet.net\/blog\/post\/30525433"},{"作者":"uioiu","文章id":31305920,"文章標題":"【新竹。竹北】大醬韓式料理 五花烤肉\/海鮮炒碼麵\/韓式中華料理\/韓國傳統湯品\/海鮮煎餅","貼文時間":"2016-01-15T00:12:00.000Z","連結":"http:\/\/uioiu.pixnet.net\/blog\/post\/31305920"},{"作者":"uioiu","文章id":31291756,"文章標題":"【新竹。竹北】錢橋涮涮鍋(高鐵店) 推薦鮮蚵","貼文時間":"2016-01-08T02:45:22.000Z","連結":"http:\/\/uioiu.pixnet.net\/blog\/post\/31291756"},{"作者":"uioiu","文章id":29838456,"文章標題":"【新竹。竹北】韓國館韓式料理~但最吸引我的是....(2015\/12更新)","貼文時間":"2016-01-01T05:56:09.000Z","連結":"http:\/\/uioiu.pixnet.net\/blog\/post\/29838456"},{"作者":"a59407908","文章id":113501369,"文章標題":"{新竹} 竹北韓式料理推薦，多樣豐富正宗韓式料理，大推入口即化人蔘雞湯大醬韓式料理","貼文時間":"2016-01-22T12:36:00.000Z","連結":"http:\/\/a59407908.pixnet.net\/blog\/post\/113501369"},{"作者":"banbi217","文章id":208219555,"文章標題":"山房Mountain House 新竹早午餐:自製塔塔魚三明治 草莓醬多到滿出來的草莓乳酪山形吐司","貼文時間":"2016-01-29T00:00:00.000Z","連結":"http:\/\/piliapp-mapping.banbi.tw\/blog\/post\/208219555"},{"作者":"bob20842","文章id":381818836,"文章標題":"新竹美食小吃-九湯屋拉麵(一碗約100元的平價拉麵，份量多，還算不錯吃)","貼文時間":"2016-01-30T03:27:07.000Z","連結":"http:\/\/bob20842.pixnet.net\/blog\/post\/381818836"},{"作者":"bob20842","文章id":361939896,"文章標題":"新竹刺身生魚片丼-鮮極日式料理1訪2訪心得(便宜CP值高，不錯吃)","貼文時間":"2016-01-28T00:53:05.000Z","連結":"http:\/\/bob20842.pixnet.net\/blog\/post\/361939896"},{"作者":"bob20842","文章id":381052834,"文章標題":"新竹小吃-12鮮築麵食、手工湯圓、冰品、紅豆湯、燒仙草一次滿足","貼文時間":"2016-01-17T00:20:10.000Z","連結":"http:\/\/bob20842.pixnet.net\/blog\/post\/381052834"},{"作者":"hrylin","文章id":43308670,"文章標題":"新竹 The Diner。來自台北的樂子美式漢堡店","貼文時間":"2016-01-23T22:14:00.000Z","連結":"http:\/\/hrylin.pixnet.net\/blog\/post\/43308670"},{"作者":"hrylin","文章id":43275412,"文章標題":"新竹老屋咖啡店。39A Cafe","貼文時間":"2016-01-18T19:31:00.000Z","連結":"http:\/\/hrylin.pixnet.net\/blog\/post\/43275412"},{"作者":"hrylin","文章id":43176580,"文章標題":"新竹城隍廟美食。百年老店阿城號","貼文時間":"2016-01-09T08:26:58.000Z","連結":"http:\/\/hrylin.pixnet.net\/blog\/post\/43176580"},{"作者":"hrylin","文章id":43195603,"文章標題":"新竹尖石北角。媽媽的店風味餐廳","貼文時間":"2016-01-02T21:40:19.000Z","連結":"http:\/\/hrylin.pixnet.net\/blog\/post\/43195603"},{"作者":"leiioo3","文章id":113257259,"文章標題":"【食】新竹市。39A Caf當日新鮮現做甜點","貼文時間":"2016-01-03T15:27:40.000Z","連結":"http:\/\/leiioo3.pixnet.net\/blog\/post\/113257259"},{"作者":"Sinea100","文章id":200754546,"文章標題":"新竹美食 ∥ 50年堅持手工自製的竹東黑輪壽司","貼文時間":"2016-01-18T09:00:00.000Z","連結":"http:\/\/sinea100.pixnet.net\/blog\/post\/200754546"}]